mk_ai/MKAI.py
mk_ai/__init__.py
MK_AI-1.0.7.dist-info/LICENSE
MK_AI-1.0.7.dist-info/METADATA
MK_AI-1.0.7.dist-info/WHEEL
MK_AI-1.0.7.dist-info/top_level.txt
MK_AI-1.0.7.dist-info/RECORD
