Metadata-Version: 2.1
Name: MK-AI
Version: 1.0.7
Summary: MK-AI is a Python package that allows you to classify stars using the MK system and machine learning.
Author-email: Jaymin Ding <jtding43@gmail.com>
License: GNU GENERAL PUBLIC LICENSE
Keywords: Star Classification,AI,ML
Classifier: Development Status :: 3 - Alpha
Classifier: Operating System :: OS Independent
Classifier: License :: OSI Approved :: GNU General Public License v3 (GPLv3)
Classifier: Programming Language :: Python :: 3
Requires-Python: >=3.6
License-File: LICENSE
Requires-Dist: selenium
Requires-Dist: requests
